py_BMD_abaqus.py
py_bmd_abaqus-0.1.9.dist-info/LICENSE
py_bmd_abaqus-0.1.9.dist-info/METADATA
py_bmd_abaqus-0.1.9.dist-info/WHEEL
py_bmd_abaqus-0.1.9.dist-info/RECORD
