Metadata-Version: 2.1
Name: py-bmd-abaqus
Version: 0.1.9
Summary: Assign bone material properties to an finite element mesh in ABAQUS. This library was created in order to automatically assign trabecular bone material property values to an ABAQUS CAE input mesh file (INP).
License: MIT
Author: Dr. David E. Cunningham, Ph.D.
Requires-Python: >=3.9,<4.0
Classifier: License :: OSI Approved :: MIT License
Classifier: Programming Language :: Python :: 3
Classifier: Programming Language :: Python :: 3.9
Classifier: Programming Language :: Python :: 3.10
Classifier: Programming Language :: Python :: 3.11
Classifier: Programming Language :: Python :: 3.12
Requires-Dist: matplotlib (>=3.9.0,<4.0.0)
Requires-Dist: numba (>=0.59.1,<0.60.0)
Requires-Dist: numpy (>=1.26.4,<2.0.0)
Requires-Dist: pandas (>=2.2.2,<3.0.0)
Requires-Dist: pydicom (>=2.4.4,<3.0.0)
